optspec
