Metadata-Version: 1.1
Name: optspec
Version: 0.6
Summary: Wrapper around getopt for option mapping, counting, and parsing.
Home-page: https://github.com/lainproliant/python3-optspec
Author: Lain Supe (lainproliant)
Author-email: lainproliant@gmail.com
License: MIT
Keywords: argv parsing commandline
Platform: UNKNOWN
Classifier: Development Status :: 3 - Alpha
Classifier: Intended Audience :: Developers
Classifier: License :: OSI Approved :: MIT License
Classifier: Programming Language :: Python :: 3
Classifier: Programming Language :: Python :: 3.2
Classifier: Programming Language :: Python :: 3.3
Classifier: Programming Language :: Python :: 3.4
Classifier: Programming Language :: Python :: 3.5
